nectaapi/__init__.py
nectaapi/comparison.py
nectaapi/schools.py
nectaapi/student.py
nectaapi/student_name.py
nectaapi/students.py
nectaapi/summary.py
nectaapi-2.0.6.dist-info/LICENSE
nectaapi-2.0.6.dist-info/METADATA
nectaapi-2.0.6.dist-info/WHEEL
nectaapi-2.0.6.dist-info/top_level.txt
nectaapi-2.0.6.dist-info/RECORD
