Metadata-Version: 2.1
Name: nectaapi
Version: 2.0.6
Summary: Fetch results of various national examinations done in Tanzania
Home-page: https://github.com/vincent-laizer/NECTA-API
Author: Tanzania Programmers (Vincent Laizer)
Author-email: <laizercorp@gmail.com>
Keywords: python,necta,api,necta api,necta tanzania,tanzania programmers
Classifier: Development Status :: 4 - Beta
Classifier: Intended Audience :: Developers
Classifier: Programming Language :: Python :: 3
Classifier: Operating System :: Unix
Classifier: Operating System :: MacOS :: MacOS X
Classifier: Operating System :: Microsoft :: Windows
License-File: LICENSE
Requires-Dist: requests
Requires-Dist: beautifulsoup4
